tools/__init__.py
tools/rich_interface.py
tools/store_in_kb.py
tools/strand.py
tools/welcome.py
strands_agents_builder/__init__.py
strands_agents_builder/strands.py
strands_agents_builder/tools.py
strands_agents_builder/handlers/__init__.py
strands_agents_builder/handlers/callback_handler.py
strands_agents_builder/models/__init__.py
strands_agents_builder/models/bedrock.py
strands_agents_builder/models/ollama.py
strands_agents_builder/utils/__init__.py
strands_agents_builder/utils/kb_utils.py
strands_agents_builder/utils/model_utils.py
strands_agents_builder/utils/welcome_utils.py
strands_agents_builder-0.1.10.dist-info/METADATA
strands_agents_builder-0.1.10.dist-info/WHEEL
strands_agents_builder-0.1.10.dist-info/entry_points.txt
strands_agents_builder-0.1.10.dist-info/licenses/LICENSE
strands_agents_builder-0.1.10.dist-info/licenses/NOTICE
strands_agents_builder-0.1.10.dist-info/RECORD
