Metadata-Version: 2.4
Name: strands-agents-builder
Version: 0.1.10
Summary: An example Strands agent demonstrating streaming, tool use, and interactivity from your terminal. This agent builder can help you to build your own agents and tools.
Project-URL: Homepage, https://github.com/strands-agents/agent-builder
Project-URL: Bug Tracker, https://github.com/strands-agents/agent-builder/issues
Project-URL: Documentation, https://strandsagents.com
Author-email: AWS <opensource@amazon.com>
License: Apache-2.0
License-File: LICENSE
License-File: NOTICE
Classifier: Development Status :: 4 - Beta
Classifier: Intended Audience :: Developers
Classifier: License :: OSI Approved :: Apache Software License
Classifier: Operating System :: OS Independent
Classifier: Programming Language :: Python :: 3
Classifier: Programming Language :: Python :: 3.10
Classifier: Programming Language :: Python :: 3.11
Classifier: Programming Language :: Python :: 3.12
Classifier: Programming Language :: Python :: 3.13
Classifier: Topic :: Scientific/Engineering :: Artificial Intelligence
Classifier: Topic :: Software Development :: Libraries :: Python Modules
Requires-Python: >=3.10
Requires-Dist: halo<1.0.0,>=0.0.31
Requires-Dist: prompt-toolkit<4.0.0,>=3.0.51
Requires-Dist: rich<15.0.0,>=14.0.0
Requires-Dist: strands-agents-tools<1.0.0,>=0.1.0
Requires-Dist: strands-agents[ollama]>=1.0.0
Provides-Extra: dev
Requires-Dist: commitizen<5.0.0,>=4.4.0; extra == 'dev'
Requires-Dist: hatch<2.0.0,>=1.0.0; extra == 'dev'
Requires-Dist: mypy<2.0.0,>=1.0.0; extra == 'dev'
Requires-Dist: pre-commit<4.2.0,>=3.2.0; extra == 'dev'
Requires-Dist: pytest>=7.0.0; extra == 'dev'
Requires-Dist: ruff<1.0.0,>=0.4.4; extra == 'dev'
Provides-Extra: docs
Requires-Dist: sphinx-autodoc-typehints<2.0.0,>=1.12.0; extra == 'docs'
Requires-Dist: sphinx-rtd-theme<2.0.0,>=1.0.0; extra == 'docs'
Requires-Dist: sphinx<6.0.0,>=5.0.0; extra == 'docs'
Provides-Extra: test
Requires-Dist: moto<6.0.0,>=5.1.0; extra == 'test'
Requires-Dist: pytest-cov<5.0.0,>=4.1.0; extra == 'test'
Requires-Dist: pytest-xdist<4.0.0,>=3.0.0; extra == 'test'
Requires-Dist: pytest<9.0.0,>=8.1.0; extra == 'test'
